sportsml/__init__.py
sportsml/cbb/__init__.py
sportsml/cbb/data/bracket.py
sportsml/cbb/data/datamodule.py
sportsml/cbb/data/dataset.py
sportsml/cbb/data/download.py
sportsml/cbb/data/features.py
sportsml/cbb/data/nodes.py
sportsml/cbb/data/utils.py
sportsml/cfb/__init__.py
sportsml/cfb/data/__init__.py
sportsml/cfb/data/datamodule.py
sportsml/cfb/data/dataset.py
sportsml/cfb/data/download.py
sportsml/cfb/data/features.py
sportsml/cfb/data/nodes.py
sportsml/cfb/data/utils.py
sportsml/cli/__init__.py
sportsml/cli/predict/__init__.py
sportsml/cli/predict/predict.py
sportsml/cli/predict/conf/__init__.py
sportsml/cli/predict/conf/conf.yaml
sportsml/cli/predict/conf/graph/cbb.yaml
sportsml/cli/predict/conf/graph/cfb.yaml
sportsml/cli/predict/conf/graph/nba.yaml
sportsml/cli/predict/conf/graph/nfl.yaml
sportsml/cli/predict/conf/team_map/cbb.yaml
sportsml/cli/predict/conf/team_map/cfb.yaml
sportsml/cli/predict/conf/team_map/nba.yaml
sportsml/cli/predict/conf/team_map/nfl.yaml
sportsml/cli/train/__init__.py
sportsml/cli/train/train.py
sportsml/cli/train/conf/__init__.py
sportsml/cli/train/conf/conf.yaml
sportsml/cli/train/conf/dm/cbb.yaml
sportsml/cli/train/conf/dm/cfb.yaml
sportsml/cli/train/conf/dm/nba.yaml
sportsml/cli/train/conf/dm/nfl.yaml
sportsml/cli/train/conf/model/gnn.yaml
sportsml/cli/train/conf/model/encoder/gcn.yaml
sportsml/cli/train/conf/model/encoder/heterogcn.yaml
sportsml/cli/train/conf/model/encoder/mean.yaml
sportsml/cli/train/conf/model/encoder/nn.yaml
sportsml/cli/train/conf/model/predictor/heteronn.yaml
sportsml/cli/train/conf/model/predictor/nn.yaml
sportsml/cli/train/conf/trainer/early_stopping.yaml
sportsml/cli/train/conf/trainer/prod.yaml
sportsml/layers/__init__.py
sportsml/layers/mlp.py
sportsml/layers/gnn/__init__.py
sportsml/layers/gnn/encoder/__init__.py
sportsml/layers/gnn/encoder/gcn.py
sportsml/layers/gnn/encoder/heterogcn.py
sportsml/layers/gnn/encoder/mean.py
sportsml/layers/gnn/encoder/nn.py
sportsml/layers/gnn/predictor/__init__.py
sportsml-0.2.1.dist-info/METADATA
sportsml-0.2.1.dist-info/WHEEL
sportsml-0.2.1.dist-info/entry_points.txt
sportsml-0.2.1.dist-info/top_level.txt
sportsml-0.2.1.dist-info/RECORD
