Metadata-Version: 2.1
Name: sportsml
Version: 0.2.1
Summary: ML for sports
License: MIT license
Requires-Python: >=3.8
Requires-Dist: captum
Requires-Dist: dgl
Requires-Dist: google-cloud-storage
Requires-Dist: hydra-core
Requires-Dist: httpx
Requires-Dist: lightning
Requires-Dist: nba-api
Requires-Dist: networkx
Requires-Dist: numpy
Requires-Dist: mlflow
Requires-Dist: pandas
Requires-Dist: pyarrow
Requires-Dist: pymongo[srv]
Requires-Dist: requests
Requires-Dist: scikit-learn
Requires-Dist: seaborn
Requires-Dist: torch
Requires-Dist: torchmetrics
